<?xml version="1.0" ?>
<!DOCTYPE bulletml SYSTEM "../bulletml.dtd">
<bulletml>
	<action  label="XWayFan">
		<repeat>
			<times>
				 $1-1
			</times>
			<action>
				<fire>
					<direction  type="sequence">
						$2
					</direction>
					<speed  type="sequence">
						$3
					</speed>
					<bullet/>
				</fire>
			</action>
		</repeat>
	</action>
	<action label="top2">
		<fire>
			<direction type="absolute">
				-10
			</direction>
			<speed>
				0
			</speed>
			<bullet>
				<action>
					<vanish/>
				</action>
			</bullet>
		</fire>
		<actionRef label="main">
			<param>
				20
			</param>
			<param>
				5
			</param>
			<param>
				1.10
			</param>
			<param>
				-0.04
			</param>
			<param>
				1.10
			</param>
			<param>
				-0.04
			</param>
		</actionRef>
		<actionRef  label="main">
			<param>
				15-$rank*6
			</param>
			<param>
				5
			</param>
			<param>
				1.06
			</param>
			<param>
				0.04
			</param>
			<param>
				1.06
			</param>
			<param>
				0.04
			</param>
		</actionRef>
		<actionRef  label="main">
			<param>
				5+$rank*20
			</param>
			<param>
				5
			</param>
			<param>
				1.10
			</param>
			<param>
				-0.04
			</param>
			<param>
				1.10
			</param>
			<param>
				-0.04
			</param>
		</actionRef>
	</action>
	<action label="top1">
		<fire>
			<direction type="absolute">
				215
			</direction>
			<speed>
				0
			</speed>
			<bullet>
				<action>
					<vanish/>
				</action>
			</bullet>
		</fire>
		<actionRef  label="main">
			<param>
				20
			</param>
			<param>
				-5
			</param>
			<param>
				1.10
			</param>
			<param>
				-0.04
			</param>
			<param>
				1.10
			</param>
			<param>
				-0.04
			</param>
		</actionRef>
		<actionRef  label="main">
			<param>
				15-$rank*6
			</param>
			<param>
				-5
			</param>
			<param>
				1.06
			</param>
			<param>
				0.04
			</param>
			<param>
				1.06
			</param>
			<param>
				0.04
			</param>
		</actionRef>
		<actionRef  label="main">
			<param>
				5+$rank*20
			</param>
			<param>
				-5
			</param>
			<param>
				1.10
			</param>
			<param>
				-0.04
			</param>
			<param>
				1.06
			</param>
			<param>
				0.04
			</param>
		</actionRef>
	</action>
	<action label="main">
		<repeat>
			<times>
				$1
			</times>
			<action>
				<fire>
					<direction type="sequence">
						36+$2
					</direction>
					<speed>
						$3
					</speed>
					<bullet/>
				</fire>
				<actionRef label="XWayFan">
					<param>
						5
					</param>
					<param>
						1
					</param>
					<param>
						$4
					</param>
				</actionRef>
				<repeat>
					<times>
						4
					</times>
					<action>
						<fire>
							<direction type="sequence">
								36
							</direction>
							<speed>
								$3
							</speed>
							<bullet/>
						</fire>
						<actionRef label="XWayFan">
							<param>
								5
							</param>
							<param>
								1
							</param>
							<param>
								$4
							</param>
						</actionRef>
					</action>
				</repeat>
				<repeat>
					<times>
						4
					</times>
					<action>
						<fire>
							<direction type="sequence">
								36
							</direction>
							<speed>
								$5
							</speed>
							<bullet/>
						</fire>
						<actionRef label="XWayFan">
							<param>
								5
							</param>
							<param>
								1
							</param>
							<param>
								$6
							</param>
						</actionRef>
					</action>
				</repeat>
				<wait>
					15
				</wait>
			</action>
		</repeat>
	</action>
</bulletml>
